solocast/solocast.py
solocast-0.2.1.dist-info/LICENSE
solocast-0.2.1.dist-info/METADATA
solocast-0.2.1.dist-info/WHEEL
solocast-0.2.1.dist-info/entry_points.txt
solocast-0.2.1.dist-info/RECORD
