Metadata-Version: 2.1
Name: solocast
Version: 0.2.1
Summary: Record audio one segment at a time
Home-page: https://gitlab.com/norrist/solocast
License: MIT
Author: Todd Norris
Author-email: norrist@gmail.com
Requires-Python: >=3.7,<4.0
Classifier: License :: OSI Approved :: MIT License
Classifier: Programming Language :: Python :: 3
Classifier: Programming Language :: Python :: 3.7
Classifier: Programming Language :: Python :: 3.8
Classifier: Programming Language :: Python :: 3.9
Classifier: Programming Language :: Python :: 3.10
Classifier: Programming Language :: Python :: 3.11
Requires-Dist: click
Project-URL: Repository, https://gitlab.com/norrist/solocast
